LICENSE.md
MANIFEST.in
README.rst
pyproject.toml
requirements.core.txt
requirements.txt
setup.py
core_linked_records_app/__init__.py
core_linked_records_app/admin.py
core_linked_records_app/apps.py
core_linked_records_app/menus.py
core_linked_records_app/models.py
core_linked_records_app/settings.py
core_linked_records_app/urls.py
core_linked_records_app.egg-info/PKG-INFO
core_linked_records_app.egg-info/SOURCES.txt
core_linked_records_app.egg-info/dependency_links.txt
core_linked_records_app.egg-info/requires.txt
core_linked_records_app.egg-info/top_level.txt
core_linked_records_app/access_control/__init__.py
core_linked_records_app/access_control/discover.py
core_linked_records_app/access_control/rights.py
core_linked_records_app/components/__init__.py
core_linked_records_app/components/blob/__init__.py
core_linked_records_app/components/blob/access_control.py
core_linked_records_app/components/blob/api.py
core_linked_records_app/components/blob/watch.py
core_linked_records_app/components/data/__init__.py
core_linked_records_app/components/data/access_control.py
core_linked_records_app/components/data/api.py
core_linked_records_app/components/data/watch.py
core_linked_records_app/components/local_id/__init__.py
core_linked_records_app/components/local_id/admin_site.py
core_linked_records_app/components/local_id/models.py
core_linked_records_app/components/oai_record/__init__.py
core_linked_records_app/components/oai_record/access_control.py
core_linked_records_app/components/oai_record/api.py
core_linked_records_app/components/pid_path/__init__.py
core_linked_records_app/components/pid_path/access_control.py
core_linked_records_app/components/pid_path/admin_site.py
core_linked_records_app/components/pid_path/api.py
core_linked_records_app/components/pid_path/models.py
core_linked_records_app/components/pid_settings/__init__.py
core_linked_records_app/components/pid_settings/access_control.py
core_linked_records_app/components/pid_settings/admin_site.py
core_linked_records_app/components/pid_settings/api.py
core_linked_records_app/components/pid_settings/models.py
core_linked_records_app/components/pid_settings/watch.py
core_linked_records_app/migrations/0001_initial.py
