Metadata-Version: 2.1
Name: core-linked-records-app
Version: 2.19.0
Summary: Linked records for the core project
Home-page: https://github.com/usnistgov/core_linked_records_app
Author: NIST IT Lab
Author-email: itl_inquiries@nist.gov
License-File: LICENSE.md
